Metadata-Version: 2.1
Name: pio2zip
Version: 1.0.0
Summary: Pack PlatformIO ESP32 firmware for upload
Home-page: https://github.com/blackshieldpt/pio2zip
Author: Bruno Teixeira
License: MIT
Project-URL: Source, https://github.com/blackshieldpt/pio2zip
Classifier: Development Status :: 5 - Production/Stable
Classifier: Intended Audience :: Developers
Classifier: License :: OSI Approved :: MIT License
Classifier: Programming Language :: Python :: 3
Classifier: Programming Language :: Python :: 3.8
Classifier: Programming Language :: Python :: 3.9
Classifier: Programming Language :: Python :: 3.10
Classifier: Programming Language :: Python :: 3.11
Classifier: Programming Language :: Python :: 3.12
Requires-Python: >=3.8
License-File: LICENSE
